robotmq/__init__.py
robotmq/utils.py
robotmq/core/robotmq_core.cpython-310-x86_64-linux-gnu.so
robotmq/core/robotmq_core.cpython-38-x86_64-linux-gnu.so
robotmq/core/robotmq_core.cpython-39-x86_64-linux-gnu.so
robotmq/core/robotmq_core.pyi
robotmq/core/include/common.h
robotmq/core/include/data_topic.h
robotmq/core/include/rmq_client.h
robotmq/core/include/rmq_message.h
robotmq/core/include/rmq_server.h
robotmq/core/src/common.cpp
robotmq/core/src/data_topic.cpp
robotmq/core/src/pybind.cpp
robotmq/core/src/rmq_client.cpp
robotmq/core/src/rmq_message.cpp
robotmq/core/src/rmq_server.cpp
robotmq.libs/libzmq-60141505.so.5.2.5
robotmq-0.1.12.dist-info/METADATA
robotmq-0.1.12.dist-info/WHEEL
robotmq-0.1.12.dist-info/top_level.txt
robotmq-0.1.12.dist-info/RECORD
robotmq-0.1.12.dist-info/licenses/LICENSE
