Metadata-Version: 2.1
Name: robotmq
Version: 0.1.12
Summary: A light-weight and flexible Robot-centric Message Queue for Python applications
Author-email: Yihuai Gao <yihuai@stanford.edu>
Project-URL: Homepage, https://github.com/yihuai-gao/robot-message-queue
Classifier: Programming Language :: Python :: 3
Classifier: License :: OSI Approved :: MIT License
Classifier: Operating System :: OS Independent
License-File: LICENSE
